pyhp/__init__.py
pyhp/app.py
pyhp/extension.py
pyhp_hypertext_preprocessor-0.1.dist-info/LICENSE
pyhp_hypertext_preprocessor-0.1.dist-info/METADATA
pyhp_hypertext_preprocessor-0.1.dist-info/WHEEL
pyhp_hypertext_preprocessor-0.1.dist-info/top_level.txt
pyhp_hypertext_preprocessor-0.1.dist-info/RECORD
