Metadata-Version: 2.1
Name: pyhp-hypertext-preprocessor
Version: 0.1
Summary: Python Hyptertext Preprocessor - like PHP, but for Python
Home-page: https://github.com/yuvipanda/pyhp
Author: YuviPanda
Author-email: yuvipanda@gmail.com
License: 3-clause BSD
Platform: any
Requires-Dist: jinja2
Requires-Dist: flask
